pytrial/__init__.py
pytrial/data/__init__.py
pytrial/data/demo_data.py
pytrial/data/drug_data.py
pytrial/data/patient_data.py
pytrial/data/site_data.py
pytrial/data/trial_data.py
pytrial/data/utils.py
pytrial/data/vocab_data.py
pytrial/model_utils/__init__.py
pytrial/model_utils/bert.py
pytrial/model_utils/drug.py
pytrial/model_utils/icd.py
pytrial/tasks/__init__.py
pytrial/tasks/indiv_outcome/__init__.py
pytrial/tasks/indiv_outcome/data.py
pytrial/tasks/indiv_outcome/losses.py
pytrial/tasks/indiv_outcome/metrics.py
pytrial/tasks/indiv_outcome/trainer.py
pytrial/tasks/indiv_outcome/causal/__init__.py
pytrial/tasks/indiv_outcome/confidence/__init__.py
pytrial/tasks/indiv_outcome/sequence/__init__.py
pytrial/tasks/indiv_outcome/sequence/base.py
pytrial/tasks/indiv_outcome/sequence/dipole.py
pytrial/tasks/indiv_outcome/sequence/raim.py
pytrial/tasks/indiv_outcome/sequence/retain.py
pytrial/tasks/indiv_outcome/sequence/rnn.py
pytrial/tasks/indiv_outcome/sequence/stagenet.py
pytrial/tasks/indiv_outcome/tabular/__init__.py
pytrial/tasks/indiv_outcome/tabular/base.py
pytrial/tasks/indiv_outcome/tabular/ft_transformer.py
pytrial/tasks/indiv_outcome/tabular/logistic_regression.py
pytrial/tasks/indiv_outcome/tabular/mlp.py
pytrial/tasks/indiv_outcome/tabular/transtab.py
pytrial/tasks/indiv_outcome/tabular/xgboost.py
pytrial/tasks/site_selection/__init__.py
pytrial/tasks/site_selection/base.py
pytrial/tasks/site_selection/data.py
pytrial/tasks/site_selection/framm.py
pytrial/tasks/site_selection/losses.py
pytrial/tasks/site_selection/metrics.py
pytrial/tasks/site_selection/pgentropy.py
pytrial/tasks/site_selection/trainer.py
pytrial/tasks/trial_outcome/__init__.py
pytrial/tasks/trial_outcome/base.py
pytrial/tasks/trial_outcome/data.py
pytrial/tasks/trial_outcome/evaluation.py
pytrial/tasks/trial_outcome/hint.py
pytrial/tasks/trial_outcome/logistic_regression.py
pytrial/tasks/trial_outcome/mlp.py
pytrial/tasks/trial_outcome/spot.py
pytrial/tasks/trial_outcome/xgboost.py
PyTrial-0.0.6.dist-info/LICENSE
PyTrial-0.0.6.dist-info/METADATA
PyTrial-0.0.6.dist-info/WHEEL
PyTrial-0.0.6.dist-info/top_level.txt
PyTrial-0.0.6.dist-info/RECORD
