Metadata-Version: 2.1
Name: PyTrial
Version: 0.0.6
Summary: PyTrial: A Python Package for Artificial Intelligence in Drug Development
Home-page: https://github.com/RyanWangZf/pytrial
Author: Zifeng Wang, Brandon Theodoru, Tianfan Fu, Jimeng Sun
Author-email: zifengw2@illinois.edu
Keywords: drug development,clinical trial,artificial intelligence,deep learning,machine learning
Classifier: Programming Language :: Python :: 3
Classifier: Programming Language :: Python :: 3.7
Classifier: Programming Language :: Python :: 3.8
Classifier: Programming Language :: Python :: 3.9
Classifier: License :: OSI Approved :: BSD License
Classifier: Operating System :: OS Independent
License-File: LICENSE
Requires-Dist: matplotlib (>=3.5.3)
Requires-Dist: networkx (>=2.6.3)
Requires-Dist: nltk (>=3.7)
Requires-Dist: numpy (>=1.21.6)
Requires-Dist: pandas (>=1.3.5)
Requires-Dist: scikit-learn (>=1.0.2)
Requires-Dist: rdkit (>=2022.9.1)
Requires-Dist: sdmetrics (==0.6.0)
Requires-Dist: ctgan (>=0.5.2)
Requires-Dist: seaborn
Requires-Dist: dill
Requires-Dist: requests
Requires-Dist: gensim
Requires-Dist: joblib
Requires-Dist: wget
Requires-Dist: tqdm
Requires-Dist: transformers
Requires-Dist: datasets
Requires-Dist: copulas
Requires-Dist: rdt
Requires-Dist: xgboost
Requires-Dist: icd10-cm
Requires-Dist: transtab
Requires-Dist: promptehr
Requires-Dist: trial2vec
Requires-Dist: accelerate
